julialg/__init__.py
julialg/array.py
julialg/core.py
julialg/formatting.py
julialg-0.1.0.dist-info/METADATA
julialg-0.1.0.dist-info/WHEEL
julialg-0.1.0.dist-info/top_level.txt
julialg-0.1.0.dist-info/RECORD
