Metadata-Version: 2.1
Name: julialg
Version: 0.1.0
Summary: Julia-style arrays in Python
Home-page: http://github.com/JWKennington/julialg
Author: James W. Kennington
Author-email: jameswkennington@gmail.com
License: MIT
Platform: UNKNOWN
